mmdbencoder/__init__.py
py_mmdb_encoder-1.0.4.dist-info/DESCRIPTION.rst
py_mmdb_encoder-1.0.4.dist-info/METADATA
py_mmdb_encoder-1.0.4.dist-info/RECORD
py_mmdb_encoder-1.0.4.dist-info/WHEEL
py_mmdb_encoder-1.0.4.dist-info/metadata.json
py_mmdb_encoder-1.0.4.dist-info/top_level.txt
