Metadata-Version: 2.0
Name: py-mmdb-encoder
Version: 1.0.4
Summary: Python MMDB encoder
Home-page: https://github.com/cloudflare/py-mmdb-encoder
Author: Louis Poinsignon / Cloudflare
Author-email: louis@cloudflare.com
License: BSD 3
Project-URL: Source, https://github.com/cloudflare/py-mmdb-encoder/
Project-URL: Bug Reports, https://github.com/cloudflare/py-mmdb-encoder/issues
Keywords: maxmind geoip network geolocation database tree development
Platform: UNKNOWN
Classifier: Development Status :: 4 - Beta
Classifier: Intended Audience :: Developers
Classifier: Topic :: Software Development :: Build Tools
Classifier: License :: OSI Approved :: BSD License
Classifier: Programming Language :: Python :: 2
Classifier: Programming Language :: Python :: 2.7
Classifier: Programming Language :: Python :: 3
Classifier: Programming Language :: Python :: 3.4
Classifier: Programming Language :: Python :: 3.5
Classifier: Programming Language :: Python :: 3.6
